syncupgrade/__init__.py
syncupgrade/cli.py
syncupgrade/cli_helper/__init__.py
syncupgrade/cli_helper/cli_utils.py
syncupgrade/cli_helper/manage_registries.py
syncupgrade/codmods/__init__.py
syncupgrade/codmods/libcst_units.py
syncupgrade/codmods/transformers_creation.py
syncupgrade/exceptions/__init__.py
syncupgrade/exceptions/custom_exceptions.py
syncupgrade/git_integration/__init__.py
syncupgrade/git_integration/git_wrapper.py
syncupgrade/git_integration/remote_git.py
syncupgrade/matchers/__init__.py
syncupgrade/matchers/node_matcher.py
syncupgrade/models/__init__.py
syncupgrade/models/cli_models.py
syncupgrade/models/enum_models.py
syncupgrade/refactor/__init__.py
syncupgrade/refactor/refactoring_methods.py
syncupgrade/utils/__init__.py
syncupgrade/utils/option_conditions.py
syncupgrade/utils/parsing_utils.py
sync_upgrade-0.1.1.dist-info/LICENSE
sync_upgrade-0.1.1.dist-info/METADATA
sync_upgrade-0.1.1.dist-info/WHEEL
sync_upgrade-0.1.1.dist-info/entry_points.txt
sync_upgrade-0.1.1.dist-info/RECORD
