Metadata-Version: 2.1
Name: sync-upgrade
Version: 0.1.1
Summary: 
Author: Moenes Ben Soussia
Author-email: moenes.bensoussia@dataminded.be
Requires-Python: >=3.9
Classifier: Programming Language :: Python :: 3
Classifier: Programming Language :: Python :: 3.9
Classifier: Programming Language :: Python :: 3.10
Classifier: Programming Language :: Python :: 3.11
Requires-Dist: coverage (>=7.2.7,<8.0.0)
Requires-Dist: gitpython (>=3.1.31,<4.0.0)
Requires-Dist: libcst (>=1.0.1,<2.0.0)
Requires-Dist: pydantic (>=2.0.2,<3.0.0)
Requires-Dist: pytest (>=7.4.0,<8.0.0)
Requires-Dist: pytest-mock (>=3.11.1,<4.0.0)
Requires-Dist: requests (>=2.31.0,<3.0.0)
Requires-Dist: rich (>=13.4.2,<14.0.0)
Requires-Dist: typer (>=0.9.0,<0.10.0)
